servicemanager/__init__.py
servicemanager/serviceresolver.py
servicemanager/smartifactrepofactory.py
servicemanager/smbintray.py
servicemanager/smcontext.py
servicemanager/smcredentials.py
servicemanager/smfile.py
servicemanager/smnexus.py
servicemanager/smport.py
servicemanager/smprocess.py
servicemanager/smrepo.py
servicemanager/smstatus.py
servicemanager/smutil.py
servicemanager/subprocess.py
servicemanager/actions/__init__.py
servicemanager/actions/actions.py
servicemanager/actions/colours.py
servicemanager/server/__init__.py
servicemanager/server/smserverlogic.py
servicemanager/service/__init__.py
servicemanager/service/smdropwizardservice.py
servicemanager/service/smexternalservice.py
servicemanager/service/smjvmservice.py
servicemanager/service/smplayservice.py
servicemanager/service/smpythonservice.py
servicemanager/service/smservice.py
servicemanager/thirdparty/__init__.py
servicemanager/thirdparty/atomicinteger.py
servicemanager/thirdparty/prettytable.py
servicemanager-1.3.0.data/scripts/sm
servicemanager-1.3.0.data/scripts/smserver
servicemanager-1.3.0.dist-info/DESCRIPTION.rst
servicemanager-1.3.0.dist-info/METADATA
servicemanager-1.3.0.dist-info/RECORD
servicemanager-1.3.0.dist-info/WHEEL
servicemanager-1.3.0.dist-info/metadata.json
servicemanager-1.3.0.dist-info/top_level.txt
