Metadata-Version: 2.0
Name: servicemanager
Version: 1.3.0
Summary: A python tool to manage developing and testing with lots of microservices
Home-page: https://github.com/hmrc/service-manager
Author: hmrc-web-operations
License: Apache Licence 2.0
Platform: UNKNOWN
Requires-Python: >2.7.13
Requires-Dist: requests (==2.8.1)
Requires-Dist: pymongo (==3.0.1)
Requires-Dist: bottle (==0.12.4)
Requires-Dist: pytest (==2.5.2)
Requires-Dist: argcomplete (==0.8.1)
